Python_Package_Project/__init__.py
Python_Package_Project/custom_exception.py
Python_Package_Project/logger.py
Python_Package_Project/youtube.py
Python_Package_Project-0.1.dist-info/LICENSE
Python_Package_Project-0.1.dist-info/METADATA
Python_Package_Project-0.1.dist-info/WHEEL
Python_Package_Project-0.1.dist-info/top_level.txt
Python_Package_Project-0.1.dist-info/RECORD
